{
  "view": "new_rising",
  "source": "steam_official_ccu + release_date",
  "schema": "v5-hist",
  "generated_at": "2026-07-22T07:43:54.322973+00:00",
  "params": {
    "launch_days": 14,
    "window_days": 14,
    "min_current": 50,
    "min_points": 3,
    "rise_min": 1.0
  },
  "count": 24,
  "rows": [
    {
      "appid": 3417410,
      "name": "Storebound",
      "ccu": 151,
      "ratio": 11.62,
      "detail": {
        "developers": [
          "Embers"
        ],
        "publishers": [
          "Embers"
        ],
        "genres": [
          "Action",
          "Adventure",
          "Indie"
        ],
        "categories": [
          "Single-player",
          "Multi-player",
          "Co-op",
          "Online Co-op",
          "Steam Achievements",
          "Custom Volume Controls",
          "Adjustable Difficulty"
        ],
        "dlc_count": 2,
        "release": "2026-07-16",
        "website": null,
        "siblings": [],
        "stats": {
          "baseline": 13,
          "peak24h": null,
          "peak_observed": 151,
          "n_points": 3
        },
        "history": [
          [
            1783749600,
            10
          ],
          [
            1784095200,
            13
          ],
          [
            1784440800,
            151
          ]
        ]
      }
    },
    {
      "appid": 4542640,
      "name": "三国：谋定天下",
      "ccu": 55,
      "ratio": 7.86,
      "detail": {
        "developers": [
          "浙江华娱网络科技有限公司"
        ],
        "publishers": [
          "上海幻电信息科技有限公司"
        ],
        "genres": [
          "Massively Multiplayer",
          "Strategy",
          "Free To Play"
        ],
        "categories": [
          "Multi-player",
          "MMO",
          "PvP",
          "Online PvP",
          "Co-op",
          "Online Co-op",
          "Cross-Platform Multiplayer"
        ],
        "dlc_count": 0,
        "release": "2026-07-17",
        "website": "https://game.bilibili.com/nslg/gw/",
        "siblings": [],
        "stats": {
          "baseline": 7,
          "peak24h": 55,
          "peak_observed": 55,
          "n_points": 240
        },
        "history": [
          [
            1784354400,
            6
          ],
          [
            1784397600,
            4
          ],
          [
            1784419200,
            13
          ],
          [
            1784440800,
            13
          ],
          [
            1784462400,
            10
          ],
          [
            1784484000,
            5
          ],
          [
            1784505600,
            10
          ],
          [
            1784527200,
            10
          ],
          [
            1784548800,
            10
          ],
          [
            1784570400,
            7
          ],
          [
            1784592000,
            15
          ],
          [
            1784613600,
            14
          ],
          [
            1784635200,
            14
          ],
          [
            1784656800,
            11
          ],
          [
            1784678400,
            52
          ],
          [
            1784700000,
            55
          ]
        ]
      }
    },
    {
      "appid": 3371260,
      "name": "列乌尼斯的挽歌 Requiem of Reuinis",
      "ccu": 667,
      "ratio": 2.07,
      "detail": {
        "developers": [
          "Zaxiquej",
          "Otogen Studio"
        ],
        "publishers": [
          "Mecrew Games"
        ],
        "genres": [
          "Indie",
          "RPG",
          "Strategy"
        ],
        "categories": [
          "Single-player",
          "Steam Achievements",
          "Custom Volume Controls",
          "Adjustable Difficulty",
          "Mouse Only Option",
          "Playable without Timed Input",
          "Save Anytime"
        ],
        "dlc_count": 0,
        "release": "2026-07-15",
        "website": "https://zaxiquej.net/gamedisplay.html",
        "siblings": [],
        "stats": {
          "baseline": 322,
          "peak24h": null,
          "peak_observed": 667,
          "n_points": 246
        },
        "history": [
          [
            1784181600,
            212
          ],
          [
            1784246400,
            276
          ],
          [
            1784268000,
            294
          ],
          [
            1784289600,
            407
          ],
          [
            1784311200,
            228
          ],
          [
            1784332800,
            378
          ],
          [
            1784354400,
            441
          ],
          [
            1784376000,
            503
          ],
          [
            1784397600,
            286
          ],
          [
            1784419200,
            504
          ],
          [
            1784440800,
            614
          ],
          [
            1784462400,
            667
          ],
          [
            1784484000,
            254
          ],
          [
            1784505600,
            374
          ],
          [
            1784527200,
            506
          ],
          [
            1784548800,
            667
          ]
        ]
      }
    },
    {
      "appid": 3467040,
      "name": "Bookshop Simulator",
      "ccu": 221,
      "ratio": 1.87,
      "detail": {
        "developers": [
          "Blep Games"
        ],
        "publishers": [
          "Blep Games"
        ],
        "genres": [
          "Action",
          "Adventure",
          "RPG",
          "Simulation",
          "Sports"
        ],
        "categories": [
          "Single-player",
          "Multi-player",
          "Co-op",
          "Online Co-op",
          "Steam Achievements",
          "Full controller support",
          "Steam Workshop"
        ],
        "dlc_count": 0,
        "release": "2026-07-20",
        "website": "https://www.bookshopsimulator.com/",
        "siblings": [],
        "stats": {
          "baseline": 118,
          "peak24h": null,
          "peak_observed": 273,
          "n_points": 3
        },
        "history": [
          [
            1783749600,
            118
          ],
          [
            1784181600,
            90
          ],
          [
            1784527200,
            221
          ]
        ]
      }
    },
    {
      "appid": 4181970,
      "name": "Full Stride",
      "ccu": 514,
      "ratio": 1.64,
      "detail": {
        "developers": [
          "Blue Bullet Inc."
        ],
        "publishers": [
          "Blue Bullet Inc."
        ],
        "genres": [
          "Indie",
          "Racing",
          "Sports"
        ],
        "categories": [
          "Single-player",
          "Multi-player",
          "PvP",
          "Online PvP",
          "Gamepad Recommended",
          "Partial Controller Support",
          "Family Sharing"
        ],
        "dlc_count": 0,
        "release": "2026-07-15",
        "website": null,
        "siblings": [],
        "stats": {
          "baseline": 313,
          "peak24h": null,
          "peak_observed": 598,
          "n_points": 246
        },
        "history": [
          [
            1784181600,
            369
          ],
          [
            1784246400,
            224
          ],
          [
            1784268000,
            465
          ],
          [
            1784289600,
            592
          ],
          [
            1784311200,
            273
          ],
          [
            1784332800,
            352
          ],
          [
            1784354400,
            468
          ],
          [
            1784376000,
            524
          ],
          [
            1784397600,
            241
          ],
          [
            1784419200,
            326
          ],
          [
            1784440800,
            522
          ],
          [
            1784462400,
            598
          ],
          [
            1784484000,
            229
          ],
          [
            1784505600,
            340
          ],
          [
            1784527200,
            448
          ],
          [
            1784548800,
            514
          ]
        ]
      }
    },
    {
      "appid": 4169820,
      "name": "永恒与星辰与日常",
      "ccu": 143,
      "ratio": 1.49,
      "detail": {
        "developers": [
          "土豆花制作组"
        ],
        "publishers": [
          "土豆花制作组"
        ],
        "genres": [
          "Adventure",
          "Indie",
          "RPG",
          "Simulation"
        ],
        "categories": [
          "Single-player",
          "Steam Achievements",
          "Camera Comfort",
          "Color Alternatives",
          "Custom Volume Controls",
          "Keyboard Only Option",
          "Mouse Only Option"
        ],
        "dlc_count": 0,
        "release": "2026-07-16",
        "website": null,
        "siblings": [],
        "stats": {
          "baseline": 96,
          "peak24h": 207,
          "peak_observed": 207,
          "n_points": 94
        },
        "history": [
          [
            1784268000,
            205
          ],
          [
            1784548800,
            152
          ],
          [
            1784570400,
            96
          ],
          [
            1784592000,
            122
          ],
          [
            1784613600,
            172
          ],
          [
            1784635200,
            207
          ],
          [
            1784656800,
            81
          ],
          [
            1784678400,
            112
          ],
          [
            1784700000,
            143
          ]
        ]
      }
    },
    {
      "appid": 4530780,
      "name": "The Hust Banhmi | Bánh Mì Bách Khoa",
      "ccu": 131,
      "ratio": 1.46,
      "detail": {
        "developers": [
          "marisa0704"
        ],
        "publishers": [
          "marisa0704"
        ],
        "genres": [
          "Casual",
          "Indie",
          "Simulation"
        ],
        "categories": [
          "Single-player",
          "Steam Achievements",
          "Family Sharing"
        ],
        "dlc_count": 0,
        "release": "2026-07-18",
        "website": null,
        "siblings": [],
        "stats": {
          "baseline": 90,
          "peak24h": 366,
          "peak_observed": 366,
          "n_points": 175
        },
        "history": [
          [
            1784440800,
            51
          ],
          [
            1784462400,
            188
          ],
          [
            1784484000,
            122
          ],
          [
            1784505600,
            71
          ],
          [
            1784527200,
            110
          ],
          [
            1784548800,
            347
          ],
          [
            1784570400,
            163
          ],
          [
            1784592000,
            114
          ],
          [
            1784613600,
            138
          ],
          [
            1784635200,
            366
          ],
          [
            1784656800,
            177
          ],
          [
            1784678400,
            117
          ],
          [
            1784700000,
            131
          ]
        ]
      }
    },
    {
      "appid": 4773930,
      "name": "君临传奇之风起云涌",
      "ccu": 65,
      "ratio": 1.44,
      "detail": {
        "developers": [
          "君临传奇之风起云涌"
        ],
        "publishers": [
          "君临传奇之风起云涌"
        ],
        "genres": [
          "Action",
          "Casual",
          "Indie",
          "Massively Multiplayer",
          "RPG",
          "Free To Play",
          "Early Access"
        ],
        "categories": [
          "Multi-player",
          "MMO",
          "In-App Purchases",
          "Family Sharing"
        ],
        "dlc_count": 0,
        "release": "2026-07-16",
        "website": null,
        "siblings": [],
        "stats": {
          "baseline": 45,
          "peak24h": 68,
          "peak_observed": 68,
          "n_points": 234
        },
        "history": [
          [
            1784268000,
            14
          ],
          [
            1784311200,
            13
          ],
          [
            1784332800,
            36
          ],
          [
            1784354400,
            48
          ],
          [
            1784376000,
            54
          ],
          [
            1784397600,
            45
          ],
          [
            1784419200,
            52
          ],
          [
            1784440800,
            58
          ],
          [
            1784462400,
            62
          ],
          [
            1784484000,
            47
          ],
          [
            1784505600,
            48
          ],
          [
            1784527200,
            58
          ],
          [
            1784548800,
            61
          ],
          [
            1784570400,
            43
          ],
          [
            1784592000,
            56
          ],
          [
            1784613600,
            63
          ],
          [
            1784635200,
            68
          ],
          [
            1784656800,
            55
          ],
          [
            1784678400,
            65
          ]
        ]
      }
    },
    {
      "appid": 2481810,
      "name": "MeowCraft",
      "ccu": 146,
      "ratio": 1.3,
      "detail": {
        "developers": [
          "Meow Studio"
        ],
        "publishers": [
          "2P Games"
        ],
        "genres": [
          "Casual",
          "Indie",
          "RPG",
          "Simulation",
          "Strategy"
        ],
        "categories": [
          "Single-player",
          "Steam Cloud",
          "Family Sharing"
        ],
        "dlc_count": 0,
        "release": "2026-07-15",
        "website": null,
        "siblings": [],
        "stats": {
          "baseline": 112,
          "peak24h": null,
          "peak_observed": 180,
          "n_points": 246
        },
        "history": [
          [
            1784181600,
            112
          ],
          [
            1784246400,
            131
          ],
          [
            1784268000,
            140
          ],
          [
            1784289600,
            167
          ],
          [
            1784311200,
            86
          ],
          [
            1784332800,
            132
          ],
          [
            1784354400,
            151
          ],
          [
            1784376000,
            172
          ],
          [
            1784397600,
            108
          ],
          [
            1784419200,
            138
          ],
          [
            1784440800,
            163
          ],
          [
            1784462400,
            180
          ],
          [
            1784484000,
            71
          ],
          [
            1784505600,
            87
          ],
          [
            1784527200,
            123
          ],
          [
            1784548800,
            151
          ]
        ]
      }
    },
    {
      "appid": 2717220,
      "name": "雀魂 -じゃんたま-",
      "ccu": 328,
      "ratio": 1.2,
      "detail": {
        "developers": [
          "Catfood Studio"
        ],
        "publishers": [
          "Yostar"
        ],
        "genres": [
          "Casual",
          "RPG",
          "Strategy"
        ],
        "categories": [
          "Multi-player",
          "PvP",
          "Online PvP",
          "Cross-Platform Multiplayer",
          "In-App Purchases",
          "Family Sharing"
        ],
        "dlc_count": 0,
        "release": "2026-07-19",
        "website": "https://mahjongsoul.com/",
        "siblings": [],
        "stats": {
          "baseline": 274,
          "peak24h": 1055,
          "peak_observed": 1055,
          "n_points": 116
        },
        "history": [
          [
            1784527200,
            326
          ],
          [
            1784548800,
            658
          ],
          [
            1784570400,
            291
          ],
          [
            1784592000,
            368
          ],
          [
            1784613600,
            816
          ],
          [
            1784635200,
            1055
          ],
          [
            1784656800,
            364
          ],
          [
            1784678400,
            87
          ],
          [
            1784700000,
            328
          ]
        ]
      }
    },
    {
      "appid": 4234260,
      "name": "主角",
      "ccu": 66,
      "ratio": 1.18,
      "detail": {
        "developers": [
          "顶顶阳光"
        ],
        "publishers": [
          "一相逢互动娱乐",
          "凤麟工作室"
        ],
        "genres": [
          "Casual",
          "Indie",
          "RPG",
          "Simulation",
          "Strategy"
        ],
        "categories": [
          "Single-player",
          "Steam Achievements",
          "Family Sharing"
        ],
        "dlc_count": 0,
        "release": "2026-07-15",
        "website": null,
        "siblings": [],
        "stats": {
          "baseline": 56,
          "peak24h": null,
          "peak_observed": 359,
          "n_points": 246
        },
        "history": [
          [
            1784095200,
            359
          ],
          [
            1784246400,
            85
          ],
          [
            1784268000,
            142
          ],
          [
            1784289600,
            176
          ],
          [
            1784311200,
            57
          ],
          [
            1784332800,
            89
          ],
          [
            1784354400,
            92
          ],
          [
            1784376000,
            108
          ],
          [
            1784397600,
            45
          ],
          [
            1784419200,
            64
          ],
          [
            1784440800,
            71
          ],
          [
            1784462400,
            81
          ],
          [
            1784484000,
            27
          ],
          [
            1784505600,
            33
          ],
          [
            1784527200,
            47
          ],
          [
            1784548800,
            66
          ]
        ]
      }
    },
    {
      "appid": 4113050,
      "name": "Wabisabi SushiDerby",
      "ccu": 90,
      "ratio": 1.15,
      "detail": {
        "developers": [
          "ITAMAE STUDIO"
        ],
        "publishers": [
          "Kodansha"
        ],
        "genres": [
          "Casual",
          "Indie",
          "Racing",
          "Simulation"
        ],
        "categories": [
          "Single-player",
          "Steam Achievements",
          "Custom Volume Controls",
          "Adjustable Difficulty",
          "Save Anytime",
          "Partial Controller Support",
          "Steam Cloud"
        ],
        "dlc_count": 0,
        "release": "2026-07-15",
        "website": "https://creatorslab.kodansha.co.jp/products/3803/",
        "siblings": [],
        "stats": {
          "baseline": 78,
          "peak24h": null,
          "peak_observed": 174,
          "n_points": 246
        },
        "history": [
          [
            1784181600,
            121
          ],
          [
            1784246400,
            76
          ],
          [
            1784268000,
            146
          ],
          [
            1784289600,
            174
          ],
          [
            1784311200,
            70
          ],
          [
            1784332800,
            114
          ],
          [
            1784354400,
            126
          ],
          [
            1784376000,
            137
          ],
          [
            1784397600,
            68
          ],
          [
            1784419200,
            87
          ],
          [
            1784440800,
            97
          ],
          [
            1784462400,
            112
          ],
          [
            1784484000,
            48
          ],
          [
            1784505600,
            68
          ],
          [
            1784527200,
            92
          ],
          [
            1784548800,
            95
          ]
        ]
      }
    },
    {
      "appid": 3641000,
      "name": "The Incident at Galley House",
      "ccu": 1615,
      "ratio": 1.15,
      "detail": {
        "developers": [
          "William Rous",
          "Evil Trout Inc."
        ],
        "publishers": [
          "Evil Trout Inc."
        ],
        "genres": [
          "Adventure"
        ],
        "categories": [
          "Single-player",
          "Steam Achievements",
          "Full controller support",
          "Adjustable Text Size",
          "Color Alternatives",
          "Custom Volume Controls",
          "Playable without Timed Input"
        ],
        "dlc_count": 0,
        "release": "2026-07-14",
        "website": "https://galley.house",
        "siblings": [],
        "stats": {
          "baseline": 1402,
          "peak24h": null,
          "peak_observed": 2237,
          "n_points": 177
        },
        "history": [
          [
            1784095200,
            1564
          ],
          [
            1784246400,
            1361
          ],
          [
            1784268000,
            1263
          ],
          [
            1784289600,
            1919
          ],
          [
            1784311200,
            1500
          ],
          [
            1784332800,
            1495
          ],
          [
            1784354400,
            1640
          ],
          [
            1784376000,
            2237
          ],
          [
            1784397600,
            1680
          ],
          [
            1784419200,
            1518
          ],
          [
            1784440800,
            1519
          ],
          [
            1784462400,
            2093
          ],
          [
            1784484000,
            1548
          ],
          [
            1784505600,
            1193
          ],
          [
            1784527200,
            1018
          ],
          [
            1784548800,
            1615
          ]
        ]
      }
    },
    {
      "appid": 4605210,
      "name": "Pet the Cat",
      "ccu": 68,
      "ratio": 1.13,
      "detail": {
        "developers": [
          "MEWSTURBO"
        ],
        "publishers": [
          "TurboCat Software"
        ],
        "genres": [
          "Action",
          "Casual",
          "Indie"
        ],
        "categories": [
          "Single-player",
          "Steam Achievements",
          "Custom Volume Controls",
          "Mouse Only Option",
          "Playable without Timed Input",
          "Save Anytime",
          "Steam Cloud"
        ],
        "dlc_count": 0,
        "release": "2026-07-17",
        "website": null,
        "siblings": [],
        "stats": {
          "baseline": 60,
          "peak24h": 156,
          "peak_observed": 177,
          "n_points": 116
        },
        "history": [
          [
            1784354400,
            161
          ],
          [
            1784548800,
            177
          ],
          [
            1784570400,
            62
          ],
          [
            1784592000,
            85
          ],
          [
            1784613600,
            153
          ],
          [
            1784635200,
            156
          ],
          [
            1784656800,
            56
          ],
          [
            1784678400,
            67
          ],
          [
            1784700000,
            68
          ]
        ]
      }
    },
    {
      "appid": 3213120,
      "name": "Machinefall",
      "ccu": 71,
      "ratio": 1.09,
      "detail": {
        "developers": [
          "by Jan Zizka"
        ],
        "publishers": [
          "by Jan Zizka"
        ],
        "genres": [
          "Strategy"
        ],
        "categories": [
          "Single-player",
          "Steam Achievements",
          "Custom Volume Controls",
          "Adjustable Difficulty",
          "Playable without Timed Input",
          "Save Anytime",
          "Stereo Sound"
        ],
        "dlc_count": 0,
        "release": "2026-07-10",
        "website": null,
        "siblings": [],
        "stats": {
          "baseline": 65,
          "peak24h": null,
          "peak_observed": 71,
          "n_points": 3
        },
        "history": [
          [
            1783749600,
            46
          ],
          [
            1784095200,
            65
          ],
          [
            1784440800,
            71
          ]
        ]
      }
    },
    {
      "appid": 3312130,
      "name": "Factory Town 2: Paradise",
      "ccu": 255,
      "ratio": 1.09,
      "detail": {
        "developers": [
          "Erik Asmussen"
        ],
        "publishers": [
          "Erik Asmussen"
        ],
        "genres": [
          "Indie",
          "Simulation",
          "Strategy",
          "Early Access"
        ],
        "categories": [
          "Single-player",
          "Steam Achievements",
          "Steam Cloud",
          "Stats",
          "Family Sharing"
        ],
        "dlc_count": 0,
        "release": "2026-07-14",
        "website": null,
        "siblings": [],
        "stats": {
          "baseline": 234,
          "peak24h": null,
          "peak_observed": 348,
          "n_points": 192
        },
        "history": [
          [
            1784095200,
            210
          ],
          [
            1784246400,
            182
          ],
          [
            1784268000,
            210
          ],
          [
            1784289600,
            279
          ],
          [
            1784311200,
            247
          ],
          [
            1784332800,
            203
          ],
          [
            1784354400,
            270
          ],
          [
            1784376000,
            348
          ],
          [
            1784397600,
            301
          ],
          [
            1784419200,
            245
          ],
          [
            1784440800,
            301
          ],
          [
            1784462400,
            324
          ],
          [
            1784484000,
            285
          ],
          [
            1784505600,
            193
          ],
          [
            1784527200,
            202
          ],
          [
            1784548800,
            275
          ]
        ]
      }
    },
    {
      "appid": 4478640,
      "name": "背包地牢: Backpack Dungeon",
      "ccu": 1276,
      "ratio": 1.08,
      "detail": {
        "developers": [
          "夜喵"
        ],
        "publishers": [
          "Shuffle Play Games"
        ],
        "genres": [
          "Indie",
          "RPG",
          "Strategy"
        ],
        "categories": [
          "Single-player",
          "Steam Achievements",
          "Adjustable Text Size",
          "Custom Volume Controls",
          "Adjustable Difficulty",
          "Mouse Only Option",
          "Playable without Timed Input"
        ],
        "dlc_count": 0,
        "release": "2026-07-14",
        "website": null,
        "siblings": [],
        "stats": {
          "baseline": 1180,
          "peak24h": null,
          "peak_observed": 1872,
          "n_points": 197
        },
        "history": [
          [
            1784095200,
            906
          ],
          [
            1784246400,
            1218
          ],
          [
            1784268000,
            1597
          ],
          [
            1784289600,
            1872
          ],
          [
            1784311200,
            1169
          ],
          [
            1784332800,
            1312
          ],
          [
            1784354400,
            1457
          ],
          [
            1784376000,
            1832
          ],
          [
            1784397600,
            1224
          ],
          [
            1784419200,
            1317
          ],
          [
            1784440800,
            1573
          ],
          [
            1784462400,
            1668
          ],
          [
            1784484000,
            637
          ],
          [
            1784505600,
            859
          ],
          [
            1784527200,
            1248
          ],
          [
            1784548800,
            1276
          ]
        ]
      }
    },
    {
      "appid": 4209160,
      "name": "Idyll Isle",
      "ccu": 108,
      "ratio": 1.07,
      "detail": {
        "developers": [
          "Future Soil Media"
        ],
        "publishers": [
          "Future Soil Media"
        ],
        "genres": [
          "Casual",
          "Indie",
          "Simulation"
        ],
        "categories": [
          "Single-player",
          "Steam Achievements",
          "Adjustable Text Size",
          "Custom Volume Controls",
          "Mouse Only Option",
          "Playable without Timed Input",
          "Save Anytime"
        ],
        "dlc_count": 0,
        "release": "2026-07-14",
        "website": null,
        "siblings": [],
        "stats": {
          "baseline": 101,
          "peak24h": null,
          "peak_observed": 170,
          "n_points": 147
        },
        "history": [
          [
            1784095200,
            69
          ],
          [
            1784246400,
            102
          ],
          [
            1784268000,
            117
          ],
          [
            1784289600,
            120
          ],
          [
            1784311200,
            74
          ],
          [
            1784332800,
            109
          ],
          [
            1784354400,
            158
          ],
          [
            1784376000,
            170
          ],
          [
            1784397600,
            101
          ],
          [
            1784419200,
            135
          ],
          [
            1784440800,
            156
          ],
          [
            1784462400,
            148
          ],
          [
            1784484000,
            45
          ],
          [
            1784505600,
            99
          ],
          [
            1784548800,
            112
          ]
        ]
      }
    },
    {
      "appid": 4829980,
      "name": "仙途放置：无尽天梯和完美装备",
      "ccu": 94,
      "ratio": 1.07,
      "detail": {
        "developers": [
          "小熠"
        ],
        "publishers": [
          "一起走过"
        ],
        "genres": [
          "Casual",
          "Indie",
          "Simulation",
          "Strategy"
        ],
        "categories": [
          "Single-player",
          "Steam Achievements",
          "Keyboard Only Option",
          "Mouse Only Option",
          "Playable without Timed Input",
          "Save Anytime",
          "Touch Only Option"
        ],
        "dlc_count": 1,
        "release": "2026-07-09",
        "website": null,
        "siblings": [],
        "stats": {
          "baseline": 88,
          "peak24h": 94,
          "peak_observed": 118,
          "n_points": 487
        },
        "history": [
          [
            1783598400,
            16
          ],
          [
            1783620000,
            25
          ],
          [
            1783641600,
            49
          ],
          [
            1783663200,
            79
          ],
          [
            1783684800,
            88
          ],
          [
            1783706400,
            73
          ],
          [
            1783728000,
            106
          ],
          [
            1783749600,
            113
          ],
          [
            1783771200,
            117
          ],
          [
            1783792800,
            96
          ],
          [
            1783814400,
            111
          ],
          [
            1783836000,
            115
          ],
          [
            1783857600,
            117
          ],
          [
            1783879200,
            88
          ],
          [
            1783900800,
            98
          ],
          [
            1783922400,
            104
          ],
          [
            1783944000,
            114
          ],
          [
            1783965600,
            92
          ],
          [
            1783987200,
            103
          ],
          [
            1784008800,
            108
          ],
          [
            1784030400,
            118
          ],
          [
            1784052000,
            89
          ],
          [
            1784073600,
            91
          ],
          [
            1784095200,
            106
          ],
          [
            1784116800,
            109
          ],
          [
            1784138400,
            80
          ],
          [
            1784160000,
            91
          ],
          [
            1784181600,
            90
          ],
          [
            1784203200,
            91
          ],
          [
            1784224800,
            71
          ],
          [
            1784246400,
            73
          ],
          [
            1784613600,
            94
          ]
        ]
      }
    },
    {
      "appid": 3201830,
      "name": "春秋异闻录",
      "ccu": 96,
      "ratio": 1.05,
      "detail": {
        "developers": [
          "Red Dragon Studio"
        ],
        "publishers": [
          "2P Games"
        ],
        "genres": [
          "Indie",
          "RPG",
          "Strategy"
        ],
        "categories": [
          "Single-player",
          "Steam Cloud",
          "Family Sharing"
        ],
        "dlc_count": 0,
        "release": "2026-07-15",
        "website": null,
        "siblings": [],
        "stats": {
          "baseline": 91,
          "peak24h": null,
          "peak_observed": 150,
          "n_points": 246
        },
        "history": [
          [
            1784181600,
            99
          ],
          [
            1784246400,
            119
          ],
          [
            1784268000,
            119
          ],
          [
            1784289600,
            150
          ],
          [
            1784311200,
            68
          ],
          [
            1784332800,
            107
          ],
          [
            1784354400,
            125
          ],
          [
            1784376000,
            134
          ],
          [
            1784397600,
            57
          ],
          [
            1784419200,
            116
          ],
          [
            1784440800,
            118
          ],
          [
            1784462400,
            130
          ],
          [
            1784484000,
            45
          ],
          [
            1784505600,
            67
          ],
          [
            1784527200,
            91
          ],
          [
            1784548800,
            109
          ]
        ]
      }
    },
    {
      "appid": 4643090,
      "name": "The NOexistenceN of Lilith",
      "ccu": 2792,
      "ratio": 1.04,
      "detail": {
        "developers": [
          "Nino Games"
        ],
        "publishers": [
          "Nino Games"
        ],
        "genres": [
          "Casual",
          "Indie",
          "RPG",
          "Simulation"
        ],
        "categories": [
          "Single-player",
          "Steam Achievements",
          "Steam Cloud",
          "Family Sharing"
        ],
        "dlc_count": 0,
        "release": "2026-07-16",
        "website": "https://www.nino-network.com/",
        "siblings": [],
        "stats": {
          "baseline": 2675,
          "peak24h": 3649,
          "peak_observed": 3733,
          "n_points": 335
        },
        "history": [
          [
            1784246400,
            2122
          ],
          [
            1784268000,
            2843
          ],
          [
            1784289600,
            3165
          ],
          [
            1784311200,
            2205
          ],
          [
            1784332800,
            2786
          ],
          [
            1784354400,
            3271
          ],
          [
            1784376000,
            3524
          ],
          [
            1784397600,
            2485
          ],
          [
            1784419200,
            3107
          ],
          [
            1784440800,
            3665
          ],
          [
            1784462400,
            3733
          ],
          [
            1784484000,
            2287
          ],
          [
            1784505600,
            2902
          ],
          [
            1784527200,
            3515
          ],
          [
            1784548800,
            3645
          ],
          [
            1784570400,
            1835
          ],
          [
            1784592000,
            2824
          ],
          [
            1784613600,
            3481
          ],
          [
            1784635200,
            3649
          ],
          [
            1784656800,
            2219
          ],
          [
            1784678400,
            2675
          ],
          [
            1784700000,
            2792
          ]
        ]
      }
    },
    {
      "appid": 948820,
      "name": "Nevergrind",
      "ccu": 54,
      "ratio": 1.0,
      "detail": {
        "developers": [
          "Neverworks Games"
        ],
        "publishers": [
          "Neverworks Games"
        ],
        "genres": [
          "Casual",
          "Indie",
          "RPG"
        ],
        "categories": [
          "Single-player",
          "Steam Achievements",
          "Steam Cloud",
          "Family Sharing"
        ],
        "dlc_count": 0,
        "release": "2026-07-14",
        "website": null,
        "siblings": [],
        "stats": {
          "baseline": 54,
          "peak24h": null,
          "peak_observed": 87,
          "n_points": 180
        },
        "history": [
          [
            1784095200,
            87
          ],
          [
            1784246400,
            65
          ],
          [
            1784268000,
            62
          ],
          [
            1784289600,
            76
          ],
          [
            1784311200,
            59
          ],
          [
            1784332800,
            66
          ],
          [
            1784354400,
            65
          ],
          [
            1784376000,
            72
          ],
          [
            1784397600,
            53
          ],
          [
            1784419200,
            62
          ],
          [
            1784440800,
            65
          ],
          [
            1784462400,
            62
          ],
          [
            1784484000,
            33
          ],
          [
            1784527200,
            50
          ],
          [
            1784548800,
            54
          ]
        ]
      }
    },
    {
      "appid": 3520820,
      "name": "挂机猫猫传",
      "ccu": 50,
      "ratio": 1.0,
      "detail": {
        "developers": [
          "狮子"
        ],
        "publishers": [
          "狮子"
        ],
        "genres": [
          "Casual",
          "Indie",
          "RPG",
          "Strategy",
          "Early Access"
        ],
        "categories": [
          "Single-player",
          "Steam Cloud",
          "Family Sharing"
        ],
        "dlc_count": 0,
        "release": "2026-07-10",
        "website": null,
        "siblings": [],
        "stats": {
          "baseline": 50,
          "peak24h": null,
          "peak_observed": 67,
          "n_points": 3
        },
        "history": [
          [
            1783749600,
            67
          ],
          [
            1784095200,
            46
          ],
          [
            1784527200,
            50
          ]
        ]
      }
    },
    {
      "appid": 2697940,
      "name": "Ascend to ZERO",
      "ccu": 975,
      "ratio": 1.0,
      "detail": {
        "developers": [
          "Flyway Games, Inc."
        ],
        "publishers": [
          "Flyway Games, Inc.",
          "KRAFTON, Inc."
        ],
        "genres": [
          "Action",
          "RPG",
          "Strategy"
        ],
        "categories": [
          "Single-player",
          "Steam Achievements",
          "Full controller support",
          "Steam Cloud",
          "Steam Leaderboards",
          "Family Sharing"
        ],
        "dlc_count": 2,
        "release": "2026-07-13",
        "website": "https://flywaygames.com/en",
        "siblings": [],
        "stats": {
          "baseline": 975,
          "peak24h": 975,
          "peak_observed": 1467,
          "n_points": 3
        },
        "history": [
          [
            1783944000,
            814
          ],
          [
            1784268000,
            1467
          ],
          [
            1784613600,
            975
          ]
        ]
      }
    }
  ]
}
