{
  "view": "prelaunch_model",
  "schema": "prelaunch_model_v1",
  "note": "羽根予想モデル（自社実績で較正したスコアカード）。跳ね確率は log-odds 合算＝解釈可能・材料が薄いほど基準確率に寄る。強さ指標 top_decile_lift は 70/30 ホールドアウトの out-of-sample。readiness=collecting の間は控えめ運用。",
  "generated_at": "2026-07-15T06:28:34.223079+00:00",
  "params": {
    "lookback_days": 180,
    "outcome_days": 14,
    "hit_threshold": 1000,
    "smooth": 8.0,
    "min_pairs": 300
  },
  "readiness": "validated",
  "n_pairs": 1689,
  "hits": 58,
  "base_rate": 0.03434,
  "features": [
    "demo_ccu",
    "twitch_peak",
    "streamers",
    "news_count",
    "web_news",
    "web_views",
    "web_reach",
    "dev_best_peak",
    "dev_best_reviews",
    "is_free",
    "genre"
  ],
  "woe": {
    "demo_ccu": {
      "none": 0.00489,
      "low": -0.71077
    },
    "twitch_peak": {
      "none": 0.0
    },
    "streamers": {
      "none": 0.0
    },
    "news_count": {
      "none": -0.96129,
      "low": 0.10013,
      "high": 1.1931
    },
    "web_news": {
      "none": 0.0
    },
    "web_views": {
      "none": -0.00996,
      "low": -0.77242,
      "mid": 1.20663
    },
    "web_reach": {
      "none": 0.0
    },
    "dev_best_peak": {
      "none": -0.23049,
      "low": 0.60977,
      "mid": 1.03564,
      "high": 1.88363
    },
    "dev_best_reviews": {
      "none": -0.22562,
      "high": 1.92553,
      "low": -0.68609
    },
    "is_free": {
      "free": -0.34855,
      "paid": 0.0711
    },
    "genre": {
      "na": -1.31328,
      "warm": -0.58274,
      "hot": 0.83317,
      "cold": -0.37107
    }
  },
  "genre_rates": {
    "Action": {
      "n": 525,
      "hits": 26,
      "rate": 0.0493
    },
    "Adventure": {
      "n": 526,
      "hits": 27,
      "rate": 0.05108
    },
    "Indie": {
      "n": 1183,
      "hits": 30,
      "rate": 0.02542
    },
    "Strategy": {
      "n": 426,
      "hits": 11,
      "rate": 0.02598
    },
    "Casual": {
      "n": 772,
      "hits": 21,
      "rate": 0.02728
    },
    "Simulation": {
      "n": 512,
      "hits": 23,
      "rate": 0.04476
    },
    "Sports": {
      "n": 70,
      "hits": 5,
      "rate": 0.06762
    },
    "Free To Play": {
      "n": 292,
      "hits": 8,
      "rate": 0.02758
    },
    "RPG": {
      "n": 349,
      "hits": 25,
      "rate": 0.0708
    },
    "Early Access": {
      "n": 261,
      "hits": 13,
      "rate": 0.04935
    },
    "Massively Multiplayer": {
      "n": 54,
      "hits": 6,
      "rate": 0.10121
    },
    "Racing": {
      "n": 29,
      "hits": 0,
      "rate": 0.00742
    },
    "Utilities": {
      "n": 2,
      "hits": 0,
      "rate": 0.02747
    },
    "Animation & Modeling": {
      "n": 1,
      "hits": 0,
      "rate": 0.03052
    },
    "Audio Production": {
      "n": 1,
      "hits": 0,
      "rate": 0.03052
    },
    "Video Production": {
      "n": 1,
      "hits": 0,
      "rate": 0.03052
    },
    "Education": {
      "n": 1,
      "hits": 0,
      "rate": 0.03052
    }
  },
  "validation_oos": {
    "eval_n": 472,
    "eval_base": 0.04449,
    "top_decile_rate": 0.21277,
    "top_decile_lift": 4.78,
    "mean_prob_hit": 0.06776,
    "mean_prob_miss": 0.01019
  },
  "feature_report": {
    "demo_ccu": {
      "low": {
        "n": 8,
        "hits": 0,
        "rate": 0.0,
        "woe": -0.71077
      },
      "none": {
        "n": 1681,
        "hits": 58,
        "rate": 0.0345,
        "woe": 0.00489
      }
    },
    "twitch_peak": {
      "none": {
        "n": 1689,
        "hits": 58,
        "rate": 0.0343,
        "woe": 0.0
      }
    },
    "streamers": {
      "none": {
        "n": 1689,
        "hits": 58,
        "rate": 0.0343,
        "woe": 0.0
      }
    },
    "news_count": {
      "high": {
        "n": 290,
        "hits": 31,
        "rate": 0.1069,
        "woe": 1.1931
      },
      "low": {
        "n": 343,
        "hits": 13,
        "rate": 0.0379,
        "woe": 0.10013
      },
      "none": {
        "n": 1056,
        "hits": 14,
        "rate": 0.0133,
        "woe": -0.96129
      }
    },
    "web_news": {
      "none": {
        "n": 1689,
        "hits": 58,
        "rate": 0.0343,
        "woe": 0.0
      }
    },
    "web_views": {
      "low": {
        "n": 9,
        "hits": 0,
        "rate": 0.0,
        "woe": -0.77242
      },
      "mid": {
        "n": 4,
        "hits": 1,
        "rate": 0.25,
        "woe": 1.20663
      },
      "none": {
        "n": 1676,
        "hits": 57,
        "rate": 0.034,
        "woe": -0.00996
      }
    },
    "web_reach": {
      "none": {
        "n": 1689,
        "hits": 58,
        "rate": 0.0343,
        "woe": 0.0
      }
    },
    "dev_best_peak": {
      "high": {
        "n": 4,
        "hits": 2,
        "rate": 0.5,
        "woe": 1.88363
      },
      "low": {
        "n": 257,
        "hits": 16,
        "rate": 0.0623,
        "woe": 0.60977
      },
      "mid": {
        "n": 6,
        "hits": 1,
        "rate": 0.1667,
        "woe": 1.03564
      },
      "none": {
        "n": 1422,
        "hits": 39,
        "rate": 0.0274,
        "woe": -0.23049
      }
    },
    "dev_best_reviews": {
      "high": {
        "n": 75,
        "hits": 16,
        "rate": 0.2133,
        "woe": 1.92553
      },
      "low": {
        "n": 235,
        "hits": 4,
        "rate": 0.017,
        "woe": -0.68609
      },
      "none": {
        "n": 1379,
        "hits": 38,
        "rate": 0.0276,
        "woe": -0.22562
      }
    },
    "is_free": {
      "free": {
        "n": 330,
        "hits": 8,
        "rate": 0.0242,
        "woe": -0.34855
      },
      "paid": {
        "n": 1359,
        "hits": 50,
        "rate": 0.0368,
        "woe": 0.0711
      }
    },
    "genre": {
      "cold": {
        "n": 254,
        "hits": 6,
        "rate": 0.0236,
        "woe": -0.37107
      },
      "hot": {
        "n": 432,
        "hits": 33,
        "rate": 0.0764,
        "woe": 0.83317
      },
      "na": {
        "n": 21,
        "hits": 0,
        "rate": 0.0,
        "woe": -1.31328
      },
      "warm": {
        "n": 982,
        "hits": 19,
        "rate": 0.0193,
        "woe": -0.58274
      }
    }
  }
}
